{
  "adult": false,
  "backdrop_path": "/zViRwl3ySscZnbXZJ2Q9wq3SeUG.jpg",
  "belongs_to_collection": null,
  "budget": 75000000,
  "genres": [
    {
      "id": 16,
      "name": "Animasyon"
    },
    {
      "id": 878,
      "name": "Bilim-Kurgu"
    },
    {
      "id": 12,
      "name": "Macera"
    },
    {
      "id": 10751,
      "name": "Aile"
    }
  ],
  "homepage": "",
  "id": 698687,
  "imdb_id": "tt8864596",
  "origin_country": [
    "US"
  ],
  "original_language": "en",
  "original_title": "Transformers One",
  "overview": "Yeminli düşmanlar olarak bilinen, ama bir zamanlar kardeş gibi birbirine bağlı dostlar olan ve Cybertron'un kaderini sonsuza dek değiştiren Optimus Prime ve Megatron'un anlatılmamış köken hikayesi.",
  "popularity": 140.42,
  "poster_path": "/5tlRopdbFf8rFjPmDY56WmnkmR3.jpg",
  "production_companies": [
    {
      "id": 24955,
      "logo_path": "/pUZAeCMZlLBBUItAl11Ip2XikdD.png",
      "name": "Paramount Animation",
      "origin_country": "US"
    },
    {
      "id": 435,
      "logo_path": "/AjzK0s2w1GtLfR4hqCjVSYi0Sr8.png",
      "name": "di Bonaventura Pictures",
      "origin_country": "US"
    },
    {
      "id": 38831,
      "logo_path": null,
      "name": "DeSanto/Murphy Productions",
      "origin_country": "US"
    },
    {
      "id": 6734,
      "logo_path": "/u55FhlG6vFNzSVKLcmnFFwLb2cc.png",
      "name": "Bay Films",
      "origin_country": "US"
    },
    {
      "id": 114732,
      "logo_path": "/tNCbisMxO5mX2X2bOQxHHQZVYnT.png",
      "name": "New Republic Pictures",
      "origin_country": "US"
    },
    {
      "id": 207846,
      "logo_path": "/1Qep9fdnqCjWFKYpwNvwy2zoRNQ.png",
      "name": "Hasbro Entertainment",
      "origin_country": "US"
    }
  ],
  "production_countries": [
    {
      "iso_3166_1": "US",
      "name": "United States of America"
    }
  ],
  "release_date": "2024-09-11",
  "revenue": 128888103,
  "runtime": 104,
  "spoken_languages": [
    {
      "english_name": "English",
      "iso_639_1": "en",
      "name": "English"
    }
  ],
  "status": "Released",
  "tagline": "Başlangıca tanık olun.",
  "title": "Transformers: Başlangıç",
  "video": false,
  "vote_average": 8.094,
  "vote_count": 1135,
  "credits": {
    "cast": [
      {
        "adult": false,
        "gender": 2,
        "id": 74568,
        "known_for_department": "Acting",
        "name": "Chris Hemsworth",
        "original_name": "Chris Hemsworth",
        "popularity": 57.515,
        "profile_path": "/piQGdoIQOF3C1EI5cbYZLAW1gfj.jpg",
        "cast_id": 6,
        "character": "Orion Pax / Optimus Prime (voice)",
        "credit_id": "644ab47eb0040a02fbe447c8",
        "order": 0
      },
      {
        "adult": false,
        "gender": 2,
        "id": 226366,
        "known_for_department": "Acting",
        "name": "Brian Tyree Henry",
        "original_name": "Brian Tyree Henry",
        "popularity": 16.97,
        "profile_path": "/1UgDnFt3OteCJQPiUelWzIR5bvT.jpg",
        "cast_id": 7,
        "character": "D-16 / Megatron (voice)",
        "credit_id": "644ab490b6abc402fd3a6d91",
        "order": 1
      },
      {
        "adult": false,
        "gender": 1,
        "id": 1245,
        "known_for_department": "Acting",
        "name": "Scarlett Johansson",
        "original_name": "Scarlett Johansson",
        "popularity": 147.421,
        "profile_path": "/lh1r1bmkEBcI3VR0AeFKGEt7JOr.jpg",
        "cast_id": 8,
        "character": "Elita-1 (voice)",
        "credit_id": "644ab49fb7abb50518d946a5",
        "order": 2
      },
      {
        "adult": false,
        "gender": 2,
        "id": 298410,
        "known_for_department": "Acting",
        "name": "Keegan-Michael Key",
        "original_name": "Keegan-Michael Key",
        "popularity": 43.434,
        "profile_path": "/vAR5gVXRG2Cl6WskXT99wgkAoH8.jpg",
        "cast_id": 9,
        "character": "B-127 (voice)",
        "credit_id": "644ab4afb7abb502fbd94708",
        "order": 3
      },
      {
        "adult": false,
        "gender": 2,
        "id": 65717,
        "known_for_department": "Acting",
        "name": "Jon Hamm",
        "original_name": "Jon Hamm",
        "popularity": 32.967,
        "profile_path": "/mrXE5fZbEDPc7BEE5G21J6qrwzi.jpg",
        "cast_id": 10,
        "character": "Sentinel Prime (voice)",
        "credit_id": "644ab4bfb6abc402fd3a6d99",
        "order": 4
      },
      {
        "adult": false,
        "gender": 2,
        "id": 884,
        "known_for_department": "Acting",
        "name": "Steve Buscemi",
        "original_name": "Steve Buscemi",
        "popularity": 37.9,
        "profile_path": "/lQKdHMxfYcCBOvwRKBAxPZVNtkg.jpg",
        "cast_id": 28,
        "character": "Starscream (voice)",
        "credit_id": "66182ce4e9da69012f81b47c",
        "order": 5
      },
      {
        "adult": false,
        "gender": 2,
        "id": 2975,
        "known_for_department": "Acting",
        "name": "Laurence Fishburne",
        "original_name": "Laurence Fishburne",
        "popularity": 38.885,
        "profile_path": "/iwx7h0AfWMm9K4sMmhru3ShSra.jpg",
        "cast_id": 11,
        "character": "Alpha Trion (voice)",
        "credit_id": "644ab4cd51e6ab037e310807",
        "order": 6
      },
      {
        "adult": false,
        "gender": 1,
        "id": 171997,
        "known_for_department": "Acting",
        "name": "Vanessa Liguori",
        "original_name": "Vanessa Liguori",
        "popularity": 2.854,
        "profile_path": "/9EkNTWHZ1U83XuQJ9VU9sldxI9g.jpg",
        "cast_id": 37,
        "character": "Airachnid (voice)",
        "credit_id": "66bed5fdc6a85414fb92f6d6",
        "order": 7
      },
      {
        "adult": false,
        "gender": 2,
        "id": 2204260,
        "known_for_department": "Acting",
        "name": "Jon Bailey",
        "original_name": "Jon Bailey",
        "popularity": 3.441,
        "profile_path": null,
        "cast_id": 38,
        "character": "Soundwave (voice)",
        "credit_id": "66bed6310000dc40c197b47d",
        "order": 8
      },
      {
        "adult": false,
        "gender": 2,
        "id": 1375036,
        "known_for_department": "Acting",
        "name": "Jason Konopisos-Alvarez",
        "original_name": "Jason Konopisos-Alvarez",
        "popularity": 1.817,
        "profile_path": "/vWunN0rdthwvaX3FOj1tmQIMylD.jpg",
        "cast_id": 39,
        "character": "Shockwave / Guard 2 (voice)",
        "credit_id": "66bed6599601bc4e28610e11",
        "order": 9
      },
      {
        "adult": false,
        "gender": 2,
        "id": 1613049,
        "known_for_department": "Acting",
        "name": "Evan Michael Lee",
        "original_name": "Evan Michael Lee",
        "popularity": 0.637,
        "profile_path": "/t5ge6vhIRLX9VjOw9Q2nInhw57T.jpg",
        "cast_id": 40,
        "character": "Jazz (voice)",
        "credit_id": "66bed66b9f53408ff44055d8",
        "order": 10
      },
      {
        "adult": false,
        "gender": 2,
        "id": 1736,
        "known_for_department": "Acting",
        "name": "James Remar",
        "original_name": "James Remar",
        "popularity": 31.352,
        "profile_path": "/ctMVpFDKKWCty60lLORf3IoJcv9.jpg",
        "cast_id": 41,
        "character": "Zeta Prime (voice)",
        "credit_id": "66bed67dfbfa4d8ee540532a",
        "order": 11
      },
      {
        "adult": false,
        "gender": 2,
        "id": 1717,
        "known_for_department": "Acting",
        "name": "Isaac C. Singleton, Jr.",
        "original_name": "Isaac C. Singleton, Jr.",
        "popularity": 2.879,
        "profile_path": "/AsVdOAbT1Ewqy6fbWZTvfKWkt4r.jpg",
        "cast_id": 42,
        "character": "Darkwing (voice)",
        "credit_id": "66bed692610373cd5c05e3bf",
        "order": 12
      },
      {
        "adult": false,
        "gender": 2,
        "id": 571562,
        "known_for_department": "Acting",
        "name": "Steve Blum",
        "original_name": "Steve Blum",
        "popularity": 19.765,
        "profile_path": "/cpO0muunoigq1WHegeOEI1AIQAo.jpg",
        "cast_id": 43,
        "character": "Announcer Bot / Guard 1 (voice)",
        "credit_id": "66bed6a8a55b05f5dd610dac",
        "order": 13
      },
      {
        "adult": false,
        "gender": 0,
        "id": 1475362,
        "known_for_department": "Acting",
        "name": "Jinny Chung",
        "original_name": "Jinny Chung",
        "popularity": 1.425,
        "profile_path": "/wpYVdTxPIBblaNyluy4ghauxpOb.jpg",
        "cast_id": 44,
        "character": "Chromia / Arcee (voice)",
        "credit_id": "66bed6c46572d160b79ba1e0",
        "order": 14
      },
      {
        "adult": false,
        "gender": 2,
        "id": 84496,
        "known_for_department": "Directing",
        "name": "Josh Cooley",
        "original_name": "Josh Cooley",
        "popularity": 3.182,
        "profile_path": "/eGN0vaFmKtqHu1nFi3Lv4roQ6P2.jpg",
        "cast_id": 45,
        "character": "Control Room Guys / PA System / Skywarp (voice)",
        "credit_id": "66bed6ef9ccf1cdefe50e6ee",
        "order": 15
      },
      {
        "adult": false,
        "gender": 2,
        "id": 4888761,
        "known_for_department": "Acting",
        "name": "Dillon Bryan",
        "original_name": "Dillon Bryan",
        "popularity": 0.094,
        "profile_path": null,
        "cast_id": 46,
        "character": "Injured Racer (voice)",
        "credit_id": "66bed7079e47b5f38f97b7ed",
        "order": 16
      }
    ],
    "crew": [
      {
        "adult": false,
        "gender": 2,
        "id": 1445426,
        "known_for_department": "Visual Effects",
        "name": "Rob Coleman",
        "original_name": "Rob Coleman",
        "popularity": 2.859,
        "profile_path": "/yNQeBPiJSytjdt3Mx4Uz7VMuunL.jpg",
        "credit_id": "6608a0f6d5191f01643086c3",
        "department": "Visual Effects",
        "job": "Animation Supervisor"
      },
      {
        "adult": false,
        "gender": 1,
        "id": 4075332,
        "known_for_department": "Visual Effects",
        "name": "Corinne Teng",
        "original_name": "Corinne Teng",
        "popularity": 0.001,
        "profile_path": null,
        "credit_id": "6608a106283ed9017c1aa593",
        "department": "Visual Effects",
        "job": "Visual Effects Producer"
      },
      {
        "adult": false,
        "gender": 2,
        "id": 1371609,
        "known_for_department": "Visual Effects",
        "name": "Stephen King",
        "original_name": "Stephen King",
        "popularity": 0.694,
        "profile_path": null,
        "credit_id": "6608a0fee6271901630cfba7",
        "department": "Visual Effects",
        "job": "Animation Supervisor"
      },
      {
        "adult": false,
        "gender": 2,
        "id": 1335195,
        "known_for_department": "Visual Effects",
        "name": "Frazer Churchill",
        "original_name": "Frazer Churchill",
        "popularity": 1.116,
        "profile_path": null,
        "credit_id": "6608a0ede6271901630cfb9c",
        "department": "Visual Effects",
        "job": "Visual Effects Supervisor"
      },
      {
        "adult": false,
        "gender": 1,
        "id": 1395449,
        "known_for_department": "Visual Effects",
        "name": "Fiona Chilton",
        "original_name": "Fiona Chilton",
        "popularity": 0.705,
        "profile_path": null,
        "credit_id": "6608a11ae6271901630cfbbf",
        "department": "Crew",
        "job": "Executive Visual Effects Producer"
      },
      {
        "adult": false,
        "gender": 2,
        "id": 113168,
        "known_for_department": "Visual Effects",
        "name": "Randal Shore",
        "original_name": "Randal Shore",
        "popularity": 1.019,
        "profile_path": null,
        "credit_id": "6608a110021cee0163491792",
        "department": "Crew",
        "job": "Executive Visual Effects Producer"
      },
      {
        "adult": false,
        "gender": 2,
        "id": 4660344,
        "known_for_department": "Production",
        "name": "Matt Quigg",
        "original_name": "Matt Quigg",
        "popularity": 0.001,
        "profile_path": null,
        "credit_id": "662146dc32cc2b00c80c4aa2",
        "department": "Production",
        "job": "Executive Producer"
      },
      {
        "adult": false,
        "gender": 2,
        "id": 1439732,
        "known_for_department": "Visual Effects",
        "name": "B.J. Farmer",
        "original_name": "B.J. Farmer",
        "popularity": 0.001,
        "profile_path": null,
        "credit_id": "662146d38a88b20185ca67c9",
        "department": "Production",
        "job": "Executive Producer"
      },
      {
        "adult": false,
        "gender": 2,
        "id": 1128684,
        "known_for_department": "Production",
        "name": "Zev Foreman",
        "original_name": "Zev Foreman",
        "popularity": 0.596,
        "profile_path": "/9TrYoHiu7tqydG7BXZQh0Odip15.jpg",
        "credit_id": "662146c4e4c9eb017cf5d1c8",
        "department": "Production",
        "job": "Executive Producer"
      },
      {
        "adult": false,
        "gender": 2,
        "id": 1516079,
        "known_for_department": "Production",
        "name": "Aaron Dem",
        "original_name": "Aaron Dem",
        "popularity": 0.749,
        "profile_path": null,
        "credit_id": "644b03be51a64e0922dceb4d",
        "department": "Production",
        "job": "Producer"
      },
      {
        "adult": false,
        "gender": 2,
        "id": 2998872,
        "known_for_department": "Production",
        "name": "Valerii An",
        "original_name": "Valerii An",
        "popularity": 0.825,
        "profile_path": null,
        "credit_id": "644b03f4596a9102fc5771df",
        "department": "Production",
        "job": "Executive Producer"
      },
      {
        "adult": false,
        "gender": 2,
        "id": 488,
        "known_for_department": "Directing",
        "name": "Steven Spielberg",
        "original_name": "Steven Spielberg",
        "popularity": 34.119,
        "profile_path": "/tZxcg19YQ3e8fJ0pOs7hjlnmmr6.jpg",
        "credit_id": "644b03da336e0104c372ff98",
        "department": "Production",
        "job": "Executive Producer"
      },
      {
        "adult": false,
        "gender": 2,
        "id": 24308,
        "known_for_department": "Production",
        "name": "Brian Goldner",
        "original_name": "Brian Goldner",
        "popularity": 2.206,
        "profile_path": null,
        "credit_id": "644b03e051a64e08b0dcebb1",
        "department": "Production",
        "job": "Executive Producer"
      },
      {
        "adult": false,
        "gender": 2,
        "id": 20208,
        "known_for_department": "Production",
        "name": "Bradley J. Fischer",
        "original_name": "Bradley J. Fischer",
        "popularity": 3.353,
        "profile_path": "/xJbGB0pDWKc4tniAQpFxhL7xLyT.jpg",
        "credit_id": "644b03ed336e01056b72ff86",
        "department": "Production",
        "job": "Executive Producer"
      },
      {
        "adult": false,
        "gender": 2,
        "id": 865,
        "known_for_department": "Production",
        "name": "Michael Bay",
        "original_name": "Michael Bay",
        "popularity": 20.753,
        "profile_path": "/rkC7lei20x5xlFH4SivAXXBh6uR.jpg",
        "credit_id": "644b03ae0c125505147a9bd4",
        "department": "Production",
        "job": "Producer"
      },
      {
        "adult": false,
        "gender": 2,
        "id": 10994,
        "known_for_department": "Production",
        "name": "Tom DeSanto",
        "original_name": "Tom DeSanto",
        "popularity": 5.27,
        "profile_path": "/cBwTvladKdseuqh0zsQNK8NXSxp.jpg",
        "credit_id": "644b0391fea0d704eb1432cd",
        "department": "Production",
        "job": "Producer"
      },
      {
        "adult": false,
        "gender": 2,
        "id": 3183,
        "known_for_department": "Production",
        "name": "Don Murphy",
        "original_name": "Don Murphy",
        "popularity": 6.837,
        "profile_path": "/xX9mLKLbsnYhdRMrdpK2ULJIe0s.jpg",
        "credit_id": "644b03a4596a91054d5771bf",
        "department": "Production",
        "job": "Producer"
      },
      {
        "adult": false,
        "gender": 1,
        "id": 13065,
        "known_for_department": "Production",
        "name": "Sarah Kliban",
        "original_name": "Sarah Kliban",
        "popularity": 0.323,
        "profile_path": null,
        "credit_id": "66bed724cd7bc1090a40546c",
        "department": "Production",
        "job": "Casting Assistant"
      },
      {
        "adult": false,
        "gender": 1,
        "id": 2499930,
        "known_for_department": "Production",
        "name": "Maureen Giblin",
        "original_name": "Maureen Giblin",
        "popularity": 0.001,
        "profile_path": null,
        "credit_id": "66bed73d1c15ca934940562a",
        "department": "Production",
        "job": "Production Manager"
      },
      {
        "adult": false,
        "gender": 2,
        "id": 1550771,
        "known_for_department": "Visual Effects",
        "name": "Dan Cortez",
        "original_name": "Dan Cortez",
        "popularity": 1.393,
        "profile_path": null,
        "credit_id": "66cd07cc5202311c7c9d9faf",
        "department": "Visual Effects",
        "job": "Visual Effects Producer"
      },
      {
        "adult": false,
        "gender": 2,
        "id": 1360012,
        "known_for_department": "Writing",
        "name": "Gabriel Ferrari",
        "original_name": "Gabriel Ferrari",
        "popularity": 2.593,
        "profile_path": "/rd9PnbwFMBCCD2nro6Yi9CZ9g06.jpg",
        "credit_id": "66d04f8317654500a1884326",
        "department": "Writing",
        "job": "Screenplay"
      },
      {
        "adult": false,
        "gender": 2,
        "id": 579281,
        "known_for_department": "Writing",
        "name": "Eric Pearson",
        "original_name": "Eric Pearson",
        "popularity": 4.212,
        "profile_path": "/S2ZAnKX48e4yGZ8nb8f0f6fuTw.jpg",
        "credit_id": "66d04f87d41af2938ba4861f",
        "department": "Writing",
        "job": "Screenplay"
      },
      {
        "adult": false,
        "gender": 2,
        "id": 1123885,
        "known_for_department": "Writing",
        "name": "Andrew Barrer",
        "original_name": "Andrew Barrer",
        "popularity": 1.731,
        "profile_path": "/6e1Q2aTYCpRV54u7N9xOKXXR0xR.jpg",
        "credit_id": "66d04f7881f25c5887e30b86",
        "department": "Writing",
        "job": "Story"
      },
      {
        "adult": false,
        "gender": 2,
        "id": 1360012,
        "known_for_department": "Writing",
        "name": "Gabriel Ferrari",
        "original_name": "Gabriel Ferrari",
        "popularity": 2.593,
        "profile_path": "/rd9PnbwFMBCCD2nro6Yi9CZ9g06.jpg",
        "credit_id": "66d04f80fa058fd8ad056975",
        "department": "Writing",
        "job": "Story"
      },
      {
        "adult": false,
        "gender": 2,
        "id": 1123885,
        "known_for_department": "Writing",
        "name": "Andrew Barrer",
        "original_name": "Andrew Barrer",
        "popularity": 1.731,
        "profile_path": "/6e1Q2aTYCpRV54u7N9xOKXXR0xR.jpg",
        "credit_id": "66d04f7bce4fe039f5473e48",
        "department": "Writing",
        "job": "Screenplay"
      },
      {
        "adult": false,
        "gender": 2,
        "id": 10952,
        "known_for_department": "Production",
        "name": "Lorenzo di Bonaventura",
        "original_name": "Lorenzo di Bonaventura",
        "popularity": 3.82,
        "profile_path": "/skMUk4eVV6e08mv31A48jdYpEPp.jpg",
        "credit_id": "5eaa300511c066001eb842e0",
        "department": "Production",
        "job": "Producer"
      },
      {
        "adult": false,
        "gender": 2,
        "id": 84496,
        "known_for_department": "Directing",
        "name": "Josh Cooley",
        "original_name": "Josh Cooley",
        "popularity": 3.182,
        "profile_path": "/eGN0vaFmKtqHu1nFi3Lv4roQ6P2.jpg",
        "credit_id": "5eaa2fb3b7fbbd001c3ad95c",
        "department": "Directing",
        "job": "Director"
      },
      {
        "adult": false,
        "gender": 2,
        "id": 24309,
        "known_for_department": "Production",
        "name": "Mark Vahradian",
        "original_name": "Mark Vahradian",
        "popularity": 2.207,
        "profile_path": "/soKYRPi4hYTnVABGkAGCRGnU87J.jpg",
        "credit_id": "5eaa301a07291c001eec8bd4",
        "department": "Production",
        "job": "Producer"
      },
      {
        "adult": false,
        "gender": 2,
        "id": 6041,
        "known_for_department": "Sound",
        "name": "Brian Tyler",
        "original_name": "Brian Tyler",
        "popularity": 6.191,
        "profile_path": "/wLPLAOcEgA9vfNuXSX1QI1ajguU.jpg",
        "credit_id": "66f05104a82b005703265537",
        "department": "Sound",
        "job": "Original Music Composer"
      },
      {
        "adult": false,
        "gender": 2,
        "id": 6041,
        "known_for_department": "Sound",
        "name": "Brian Tyler",
        "original_name": "Brian Tyler",
        "popularity": 6.191,
        "profile_path": "/wLPLAOcEgA9vfNuXSX1QI1ajguU.jpg",
        "credit_id": "66f0511b6fd7cc7d423b72e0",
        "department": "Sound",
        "job": "Conductor"
      },
      {
        "adult": false,
        "gender": 2,
        "id": 1984302,
        "known_for_department": "Production",
        "name": "Olivier Dumont",
        "original_name": "Olivier Dumont",
        "popularity": 0.211,
        "profile_path": null,
        "credit_id": "671999431ea33928297ce98a",
        "department": "Production",
        "job": "Executive Producer"
      },
      {
        "adult": false,
        "gender": 0,
        "id": 1463446,
        "known_for_department": "Acting",
        "name": "Christopher Batty",
        "original_name": "Christopher Batty",
        "popularity": 0.001,
        "profile_path": null,
        "credit_id": "671999e45be9e8759da6d701",
        "department": "Camera",
        "job": "Other"
      },
      {
        "adult": false,
        "gender": 0,
        "id": 2002335,
        "known_for_department": "Visual Effects",
        "name": "Jason William Scheier",
        "original_name": "Jason William Scheier",
        "popularity": 0.4,
        "profile_path": null,
        "credit_id": "67199a05e833d92ef05fcc2d",
        "department": "Art",
        "job": "Production Design"
      },
      {
        "adult": false,
        "gender": 1,
        "id": 70658,
        "known_for_department": "Editing",
        "name": "Lynn Hobson",
        "original_name": "Lynn Hobson",
        "popularity": 0.211,
        "profile_path": null,
        "credit_id": "67199a175be9e8759da6d710",
        "department": "Editing",
        "job": "Editor"
      },
      {
        "adult": false,
        "gender": 2,
        "id": 2107419,
        "known_for_department": "Writing",
        "name": "Bobby Rubio",
        "original_name": "Bobby Rubio",
        "popularity": 0.699,
        "profile_path": "/x1uk3z1CCS5w1Exgh0PX4084FsT.jpg",
        "credit_id": "67199a295d0de89042d8d551",
        "department": "Writing",
        "job": "Head of Story"
      },
      {
        "adult": false,
        "gender": 0,
        "id": 2080754,
        "known_for_department": "Art",
        "name": "Amy Beth Christenson",
        "original_name": "Amy Beth Christenson",
        "popularity": 0.001,
        "profile_path": null,
        "credit_id": "67199a7e9ff681d9e0a3b5f0",
        "department": "Visual Effects",
        "job": "Character Designer"
      },
      {
        "adult": false,
        "gender": 0,
        "id": 2001475,
        "known_for_department": "Art",
        "name": "Gerald de Jesus",
        "original_name": "Gerald de Jesus",
        "popularity": 0.001,
        "profile_path": null,
        "credit_id": "67199a8c4be15469e70d754a",
        "department": "Art",
        "job": "Art Direction"
      },
      {
        "adult": false,
        "gender": 0,
        "id": 2285887,
        "known_for_department": "Visual Effects",
        "name": "Alex Prichard",
        "original_name": "Alex Prichard",
        "popularity": 0.001,
        "profile_path": null,
        "credit_id": "67199ab1fefd1e0510ffde9c",
        "department": "Visual Effects",
        "job": "Visual Effects Supervisor"
      },
      {
        "adult": false,
        "gender": 1,
        "id": 1395449,
        "known_for_department": "Visual Effects",
        "name": "Fiona Chilton",
        "original_name": "Fiona Chilton",
        "popularity": 0.705,
        "profile_path": null,
        "credit_id": "67199ac54be15469e70d7553",
        "department": "Visual Effects",
        "job": "Visual Effects Producer"
      },
      {
        "adult": false,
        "gender": 0,
        "id": 1679528,
        "known_for_department": "Visual Effects",
        "name": "Kim Ooi",
        "original_name": "Kim Ooi",
        "popularity": 1.583,
        "profile_path": null,
        "credit_id": "67199adefefd1e0510ffdea9",
        "department": "Visual Effects",
        "job": "Animation Supervisor"
      },
      {
        "adult": false,
        "gender": 2,
        "id": 84127,
        "known_for_department": "Production",
        "name": "Greg Mooradian",
        "original_name": "Greg Mooradian",
        "popularity": 0.521,
        "profile_path": null,
        "credit_id": "67199b374542e371fe0a3fc5",
        "department": "Production",
        "job": "Executive Producer"
      },
      {
        "adult": false,
        "gender": 0,
        "id": 1718936,
        "known_for_department": "Acting",
        "name": "Cyrus Shaki-Khan",
        "original_name": "Cyrus Shaki-Khan",
        "popularity": 0.001,
        "profile_path": null,
        "credit_id": "67199b7fb3d5cbb842f3d054",
        "department": "Production",
        "job": "Co-Producer"
      },
      {
        "adult": false,
        "gender": 0,
        "id": 5018336,
        "known_for_department": "Production",
        "name": "Ian Jude Santa Ana",
        "original_name": "Ian Jude Santa Ana",
        "popularity": 0.001,
        "profile_path": null,
        "credit_id": "67199b989ff681d9e0a3b621",
        "department": "Production",
        "job": "Associate Producer"
      },
      {
        "adult": false,
        "gender": 0,
        "id": 2524251,
        "known_for_department": "Writing",
        "name": "Matthias De Clercq",
        "original_name": "Matthias De Clercq",
        "popularity": 0.421,
        "profile_path": null,
        "credit_id": "67199c005be9e8759da6d76d",
        "department": "Writing",
        "job": "Story Artist"
      },
      {
        "adult": false,
        "gender": 0,
        "id": 2806604,
        "known_for_department": "Directing",
        "name": "Micah Gunnell",
        "original_name": "Micah Gunnell",
        "popularity": 0.337,
        "profile_path": null,
        "credit_id": "67199c0c4542e371fe0a3fe5",
        "department": "Writing",
        "job": "Story Artist"
      },
      {
        "adult": false,
        "gender": 2,
        "id": 1455548,
        "known_for_department": "Writing",
        "name": "Kevin R. Adams",
        "original_name": "Kevin R. Adams",
        "popularity": 2.18,
        "profile_path": null,
        "credit_id": "67199c17b3d5cbb842f3d089",
        "department": "Writing",
        "job": "Story Artist"
      },
      {
        "adult": false,
        "gender": 0,
        "id": 5018339,
        "known_for_department": "Writing",
        "name": "Lewie Kerr",
        "original_name": "Lewie Kerr",
        "popularity": 0.001,
        "profile_path": null,
        "credit_id": "67199c2eb3d5cbb842f3d09a",
        "department": "Writing",
        "job": "Story Artist"
      },
      {
        "adult": false,
        "gender": 2,
        "id": 1055222,
        "known_for_department": "Art",
        "name": "David Krentz",
        "original_name": "David Krentz",
        "popularity": 0.528,
        "profile_path": null,
        "credit_id": "67199c365d0de89042d8d581",
        "department": "Writing",
        "job": "Story Artist"
      },
      {
        "adult": false,
        "gender": 0,
        "id": 1393015,
        "known_for_department": "Visual Effects",
        "name": "Joe Ksander",
        "original_name": "Joe Ksander",
        "popularity": 1.276,
        "profile_path": null,
        "credit_id": "67199c434542e371fe0a3ff6",
        "department": "Writing",
        "job": "Story Artist"
      },
      {
        "adult": false,
        "gender": 0,
        "id": 5018341,
        "known_for_department": "Writing",
        "name": "Zhi Kang Lim",
        "original_name": "Zhi Kang Lim",
        "popularity": 0.001,
        "profile_path": null,
        "credit_id": "67199c5334c0fabd681c4fa9",
        "department": "Writing",
        "job": "Story Artist"
      },
      {
        "adult": false,
        "gender": 0,
        "id": 2084142,
        "known_for_department": "Art",
        "name": "Ahmed Nasri",
        "original_name": "Ahmed Nasri",
        "popularity": 0.001,
        "profile_path": null,
        "credit_id": "67199c5e9ff681d9e0a3b660",
        "department": "Writing",
        "job": "Story Artist"
      },
      {
        "adult": false,
        "gender": 0,
        "id": 1453606,
        "known_for_department": "Writing",
        "name": "Dean Roberts",
        "original_name": "Dean Roberts",
        "popularity": 0.001,
        "profile_path": null,
        "credit_id": "67199c68b3d5cbb842f3d09d",
        "department": "Writing",
        "job": "Story Artist"
      },
      {
        "adult": false,
        "gender": 0,
        "id": 1314040,
        "known_for_department": "Writing",
        "name": "Adam Temple",
        "original_name": "Adam Temple",
        "popularity": 0.001,
        "profile_path": null,
        "credit_id": "67199c7234c0fabd681c4fad",
        "department": "Writing",
        "job": "Story Artist"
      },
      {
        "adult": false,
        "gender": 0,
        "id": 5018343,
        "known_for_department": "Writing",
        "name": "Fabien Tong",
        "original_name": "Fabien Tong",
        "popularity": 0.001,
        "profile_path": null,
        "credit_id": "67199c849ff681d9e0a3b671",
        "department": "Writing",
        "job": "Story Artist"
      },
      {
        "adult": false,
        "gender": 2,
        "id": 1331388,
        "known_for_department": "Editing",
        "name": "Vivek 'Vic' Sharma",
        "original_name": "Vivek 'Vic' Sharma",
        "popularity": 0.735,
        "profile_path": null,
        "credit_id": "67199c96b3d5cbb842f3d0a5",
        "department": "Editing",
        "job": "Associate Editor"
      },
      {
        "adult": false,
        "gender": 0,
        "id": 1564735,
        "known_for_department": "Editing",
        "name": "Noelleen Westcombe",
        "original_name": "Noelleen Westcombe",
        "popularity": 0.574,
        "profile_path": null,
        "credit_id": "67199ca59ff681d9e0a3b67c",
        "department": "Editing",
        "job": "First Assistant Editor"
      },
      {
        "adult": false,
        "gender": 0,
        "id": 3887255,
        "known_for_department": "Editing",
        "name": "Arin Mathern",
        "original_name": "Arin Mathern",
        "popularity": 0.001,
        "profile_path": null,
        "credit_id": "67199cb7b3d5cbb842f3d0ae",
        "department": "Editing",
        "job": "Assistant Editor"
      },
      {
        "adult": false,
        "gender": 1,
        "id": 7903,
        "known_for_department": "Production",
        "name": "Mary Hidalgo",
        "original_name": "Mary Hidalgo",
        "popularity": 5.893,
        "profile_path": null,
        "credit_id": "6720e8f7c7802cc5035ab186",
        "department": "Production",
        "job": "Casting"
      },
      {
        "adult": false,
        "gender": 2,
        "id": 8166,
        "known_for_department": "Sound",
        "name": "Juan Peralta",
        "original_name": "Juan Peralta",
        "popularity": 2.997,
        "profile_path": "/zj1TALZsU3El6cuwtlCpo0hcpoH.jpg",
        "credit_id": "679e659428bb97ddd3954669",
        "department": "Sound",
        "job": "Sound Re-Recording Mixer"
      },
      {
        "adult": false,
        "gender": 2,
        "id": 1378828,
        "known_for_department": "Sound",
        "name": "Michael Semanick",
        "original_name": "Michael Semanick",
        "popularity": 2.551,
        "profile_path": "/poGaVc3vdZmkZCvSLNIkkIsxffj.jpg",
        "credit_id": "679e65bba893591415954679",
        "department": "Sound",
        "job": "Sound Re-Recording Mixer"
      },
      {
        "adult": false,
        "gender": 0,
        "id": 1463446,
        "known_for_department": "Acting",
        "name": "Christopher Batty",
        "original_name": "Christopher Batty",
        "popularity": 0.001,
        "profile_path": null,
        "credit_id": "67b7bfdba2284666f1eb1a90",
        "department": "Camera",
        "job": "Director of Photography"
      }
    ]
  },
  "keywords": {
    "keywords": [
      {
        "id": 10542,
        "name": "based on toy"
      },
      {
        "id": 10891,
        "name": "giant robot"
      },
      {
        "id": 179430,
        "name": "aftercreditsstinger"
      },
      {
        "id": 179431,
        "name": "duringcreditsstinger"
      },
      {
        "id": 222863,
        "name": "buddy movie"
      },
      {
        "id": 235583,
        "name": "brothers-in-arms relationship"
      },
      {
        "id": 242214,
        "name": "origin story"
      },
      {
        "id": 281585,
        "name": "inspirational"
      },
      {
        "id": 295150,
        "name": "friends to enemies"
      },
      {
        "id": 303848,
        "name": "alien robot"
      },
      {
        "id": 314730,
        "name": "suspenseful"
      },
      {
        "id": 325782,
        "name": "cheerful"
      },
      {
        "id": 325812,
        "name": "exhilarated"
      }
    ]
  },
  "videos": {
    "results": []
  },
  "recommendations": {
    "page": 1,
    "results": [
      {
        "backdrop_path": "/mQZJoIhTEkNhCYAqcHrQqhENLdu.jpg",
        "id": 1184918,
        "title": "Vahşi Robot",
        "original_title": "The Wild Robot",
        "overview": "Bu destansı macera, ıssız bir adaya düşen ve zorlu çevre koşullarına uyum sağlamayı öğrenmesi gereken bir robotun -ROZZUM ünite 7134’ün, kısaca “Roz”un- yavaş yavaş adadaki hayvanlarla ilişki kurmasını ve yetim bir kaz yavrusunun evlat edinmesini konu alıyor.",
        "poster_path": "/wIPEakWqEBfpqtw7dXaVUQ5Qz8E.jpg",
        "media_type": "movie",
        "adult": false,
        "original_language": "en",
        "genre_ids": [
          16,
          878,
          10751
        ],
        "popularity": 300.801,
        "release_date": "2024-09-12",
        "video": false,
        "vote_average": 8.338,
        "vote_count": 4459
      },
      {
        "backdrop_path": "/8NvaYUSmpe56dBz7B5m3jSpJI3t.jpg",
        "id": 1857,
        "title": "The Transformers: The Movie",
        "original_title": "The Transformers: The Movie",
        "overview": "The Transformers: The Movie adı ile sinemalara giren film, popüler Transformers dizisinin ilk sinema uyarlamasıdır ve çizgi filmdir. ABD'de 8 Ağustos 1986'da, Avustralya'da 1 Aralık 1986'da, Japonya'da 9 Ağustos 1989'da, İngiltere'de ise 4 Mayıs 2007'de vizyona girmiştir. Seslendirenler ise: Norman Alden, Jack Angel, Michael Bell, Peter Cullen, Gregg Berger, Susan Blu, Corey Burton, BJ Davis, Paul Eiding ve Regis Cordic'dir. Türkiye'de NTV ve D Çocuk'ta çizgi filmi yayınlanmaktadır.Filmi ile bir alakası yoktur.",
        "poster_path": "/j4HTorvJdGOuIgGyE56fMCLmcCg.jpg",
        "media_type": "movie",
        "adult": false,
        "original_language": "en",
        "genre_ids": [
          16,
          878,
          28,
          12,
          10751
        ],
        "popularity": 18.285,
        "release_date": "1986-08-08",
        "video": false,
        "vote_average": 7.1,
        "vote_count": 528
      },
      {
        "backdrop_path": "/vZG7PrX9HmdgL5qfZRjhJsFYEIA.jpg",
        "id": 912649,
        "title": "Venom: Son Dans",
        "original_title": "Venom: The Last Dance",
        "overview": "Venom: Son Dans (2024), Eddie Brock ve Venom’un hikâyesinin son bölümünü işleyen bir bilim kurgu, aksiyon ve macera filmidir. Bu filmde, Eddie ve simbiyotu Venom, artık bir arada yaşamaya alışmışlardır. Ancak, kendilerini hem dünyalarından hem de başka düşmanlardan kaçmak zorunda kalan birer kaçak olarak bulurlar. Bu durum, Eddie ve Venom’un hayatta kalmak için güçlü bir ortaklık kurmasını gerektirir.",
        "poster_path": "/xIjGt7bSU7hgWtYwccfufiM1wWZ.jpg",
        "media_type": "movie",
        "adult": false,
        "original_language": "en",
        "genre_ids": [
          28,
          878,
          12
        ],
        "popularity": 505.652,
        "release_date": "2024-10-22",
        "video": false,
        "vote_average": 6.8,
        "vote_count": 2966
      },
      {
        "backdrop_path": "/7u6fQagw5BON5Xvg82MuPJ2REGB.jpg",
        "id": 976734,
        "title": "Siyah Kanarya",
        "original_title": "Canary Black",
        "overview": "Üst düzey CIA ajanı Avery Graves, kaçırılan kocasını kurtarmak için kendi ülkesine ihanet etmesi için teröristler tarafından şantaja uğrar. Ekibinden koparılan Graves, hayatta kalmak ve kaçıranların istediği istihbaratı bulmaya yardım etmek için yeraltı dünyasındaki bağlantılarına başvurur.",
        "poster_path": "/9OKK3CCmss3JQogOEGCTGchmo18.jpg",
        "media_type": "movie",
        "adult": false,
        "original_language": "en",
        "genre_ids": [
          28,
          53,
          80
        ],
        "popularity": 66.571,
        "release_date": "2024-10-10",
        "video": false,
        "vote_average": 6.2,
        "vote_count": 392
      },
      {
        "backdrop_path": "/mnNlo4jB9zmoyu0MBMPBQWWAnxn.jpg",
        "id": 1111644,
        "title": "Ocean Rescue",
        "original_title": "深海危机",
        "overview": "The first maritime anti-terrorist film in China tells the story of the anti-terrorist personnel of the Chinese police who work closely with the Chinese Navy to finally end the crisis.",
        "poster_path": "/1PHeKpikcEAUtAr3CjVxUgrX7Dc.jpg",
        "media_type": "movie",
        "adult": false,
        "original_language": "zh",
        "genre_ids": [
          28
        ],
        "popularity": 0.921,
        "release_date": "2023-04-15",
        "video": false,
        "vote_average": 5.3,
        "vote_count": 3
      },
      {
        "backdrop_path": "/3kvS6Ws5usxSk1wIbKZ7YPug2V2.jpg",
        "id": 1103621,
        "title": "How to Make Millions Before Grandma Dies",
        "original_title": "หลานม่า",
        "overview": "M, a university dropout low on money and luck, volunteers to take care of his terminally ill grandmother, in the hope of pocketing an inheritance.",
        "poster_path": "/9Xa0Grd2jq2lM2gqcoTB4F9TjMd.jpg",
        "media_type": "movie",
        "adult": false,
        "original_language": "th",
        "genre_ids": [
          18
        ],
        "popularity": 25.29,
        "release_date": "2024-04-04",
        "video": false,
        "vote_average": 8.1,
        "vote_count": 143
      },
      {
        "backdrop_path": "/uGmYqxh8flqkudioyFtD7IJSHxK.jpg",
        "id": 889737,
        "title": "Joker: İkili Delilik",
        "original_title": "Joker: Folie à Deux",
        "overview": "\"Joker: Folie à Deux,\" Türkçe adıyla Joker: İkili Delilik, 2024 yapımı aksiyon, dram ve müzikal türünde bir devam filmi. Todd Phillips'in yönetmenliğinde çekilen film, 2019'da vizyona giren ve büyük başarı elde eden Joker filminin devamı niteliğinde. Başrolde yine Joaquin Phoenix, Arthur Fleck karakterine hayat veriyor. Ona Harley Quinn rolüyle Lady Gaga eşlik ediyor. Ayrıca Brendan Gleeson, Catherine Keener, Zazie Beetz ve Steve Coogan da önemli rollerde yer alıyor.  Joker olarak kimliğine büründükten sonra Arthur'un, Arkham Akıl Hastanesi'nde yaşadığı süreç ve içsel mücadelesini merkeze alıyor. Bu zorlu dönemde Harley Quinn ile tanışması, ona hem romantik bir bağ hem de sanatsal bir keşif sunuyor.​  Film 4 Ekim 2024'te vizyona girdi ve IMDb puanı şu an 8.0 civarında. Yönetmenliğini Todd Phillips üstlenirken, senaryo Todd Phillips ve Scott Silver'a ait.",
        "poster_path": "/tXF2p2hthwXDXvCyXcwWuJKgaHD.jpg",
        "media_type": "movie",
        "adult": false,
        "original_language": "en",
        "genre_ids": [
          18,
          80,
          53
        ],
        "popularity": 65.005,
        "release_date": "2024-10-01",
        "video": false,
        "vote_average": 5.489,
        "vote_count": 2193
      },
      {
        "backdrop_path": "/rOmUuQEZfPXglwFs5ELLLUDKodL.jpg",
        "id": 845781,
        "title": "Kod Adı: Kırmızı",
        "original_title": "Red One",
        "overview": "Kuzey Kutbu'nun Güvenlik Şefi (Dwayne Johnson), Noel'i kurtarmak için dünyanın en kötü şöhretli ödül avcısıyla (Chris Evans) dünyayı dolaşacakları aksiyon dolu bir görevde bir araya gelmek zorunda kalır.",
        "poster_path": "/ymEu97tJ8h2sUAhaw8CU3MGTi9v.jpg",
        "media_type": "movie",
        "adult": false,
        "original_language": "en",
        "genre_ids": [
          28,
          14,
          35
        ],
        "popularity": 238.025,
        "release_date": "2024-10-31",
        "video": false,
        "vote_average": 7.069,
        "vote_count": 2360
      },
      {
        "backdrop_path": "/n6KXCV9jqUDDL5HCIoKHQ8kD9Fq.jpg",
        "id": 835113,
        "title": "Woman of the Hour",
        "original_title": "Woman of the Hour",
        "overview": "Woman of the Hour, 1970'lerin popüler çöpçatanlık programının yarışmacılarından Cheryl Bradshaw'ın hikayesini konu ediyor. Popüler evlendirme programı “The Dating Show”a katılan Cheryl Bradshaw'ınbir bekarlığa veda partisi için yakışıklı yarışmacı Rodney Alcala'yı seçer. Ancak Alcala, pek de göründüğü gibi biri değildir.O, Amerika Birleşik Devletleri'ndeki en büyük seri katillerden biridir.",
        "poster_path": "/nc9ZqrJFbcUdlMg9lxXXtJb24jU.jpg",
        "media_type": "movie",
        "adult": false,
        "original_language": "en",
        "genre_ids": [
          80,
          18,
          53
        ],
        "popularity": 25.423,
        "release_date": "2024-10-03",
        "video": false,
        "vote_average": 6.4,
        "vote_count": 696
      },
      {
        "backdrop_path": "/t98L9uphqBSNn2Mkvdm3xSFCQyi.jpg",
        "id": 933260,
        "title": "Cevher",
        "original_title": "The Substance",
        "overview": "Bir aerobik programının yıldızı olan Elisabeth Sparkle, ilerleyen yaşı yüzünden 50. doğumgününde kovulunca yıkılır. Gizemli bir laboratuvar ona, damarlarına zerk edildiğinde \"kendisinin daha iyi bir versiyonunu\" ortaya çıkaracak mucizevi bir maddeyi kullanması önerisiyle yaklaşır. David Cronenberg, John Carpenter, David Lynch ve Michael Haneke’den esinlenen yönetmen Coralie Fargeat’ın büyük ses getiren ilk filmi İntikam’ın (2017) ardından çektiği bu çağdaş zaman eleştirisi alabildiğine stilize, zihinlerde kesinlikle iz bırakacak, zaman zaman kanlı, dehşet verici ve bazen de komik. Her yanıyla olağanüstü Demi Moore, kendi imajını da acımasızca yansıtan Elisabeth’i canlandırırken alabildiğine cesur.",
        "poster_path": "/rNrBHeqnDA8aHIz9eYkBskcKhq7.jpg",
        "media_type": "movie",
        "adult": false,
        "original_language": "en",
        "genre_ids": [
          27,
          878
        ],
        "popularity": 428.651,
        "release_date": "2024-09-07",
        "video": false,
        "vote_average": 7.1,
        "vote_count": 4083
      },
      {
        "backdrop_path": "/iR79ciqhtaZ9BE7YFA1HpCHQgX4.jpg",
        "id": 1100782,
        "title": "Gülümse 2",
        "original_title": "Smile 2",
        "overview": "Yeni bir dünya turuna çıkmak üzere olan küresel pop fenomeni Skye Riley(Naomi Scott), giderek daha korkunç ve açıklanamaz olaylar yaşamaya başlar. Artan dehşet ve şöhretin baskısından bunalan Skye, kontrolden çıkmadan önce hayatının kontrolünü yeniden kazanmak için karanlık geçmişiyle yüzleşmek zorunda kalır.",
        "poster_path": "/eJ0KIFewo6jw51f2Dy0iujEXmqd.jpg",
        "media_type": "movie",
        "adult": false,
        "original_language": "en",
        "genre_ids": [
          27,
          9648
        ],
        "popularity": 154.38,
        "release_date": "2024-10-16",
        "video": false,
        "vote_average": 6.6,
        "vote_count": 1338
      },
      {
        "backdrop_path": "/n4ycOGj2tRLfINTJQ3wl0vNYqpR.jpg",
        "id": 592983,
        "title": "Büyülü Ailem",
        "original_title": "Spellbound",
        "overview": "Ebeveynleri güçlü bir büyüyle dev canavarlara dönüşen genç prensesin, çok geç olmadan büyüyü bozmak için hiç bilmediği yerlere doğru bir yolculuk yapması gerekir.",
        "poster_path": "/8OcWJkenrZ6mA8lvRSAhNXts3ps.jpg",
        "media_type": "movie",
        "adult": false,
        "original_language": "en",
        "genre_ids": [
          16,
          14,
          10751,
          12,
          35
        ],
        "popularity": 83.369,
        "release_date": "2024-11-22",
        "video": false,
        "vote_average": 6.7,
        "vote_count": 234
      },
      {
        "backdrop_path": "/iPHsjvbFyGbeCEDC7u8Ib8U1zS6.jpg",
        "id": 947891,
        "title": "My Old Ass",
        "original_title": "My Old Ass",
        "overview": "An 18th birthday mushroom trip brings free-spirited Elliott face-to-face with her wisecracking 39-year-old self. But when Elliott’s \"old ass\" starts handing out warnings about what her younger self should and shouldn't do, Elliott realizes she has to rethink everything about family, love, and what's becoming a transformative summer.",
        "poster_path": "/yUs4Sw9AyTg2sA1qWBkNpD2mGSj.jpg",
        "media_type": "movie",
        "adult": false,
        "original_language": "en",
        "genre_ids": [
          35,
          18,
          10749
        ],
        "popularity": 47.655,
        "release_date": "2024-09-13",
        "video": false,
        "vote_average": 6.9,
        "vote_count": 271
      },
      {
        "backdrop_path": "/by8z9Fe8y7p4jo2YlW2SZDnptyT.jpg",
        "id": 533535,
        "title": "Deadpool & Wolverine",
        "original_title": "Deadpool & Wolverine",
        "overview": "Wade Wilson’ın bir paralı asker olarak geçirdiği günler ve Deadpool kimliği artık geride kalmıştır. O şimdi sivil hayatta varlık göstermek için çabalar. Wade, yeni hayatına alışmaya çalışırken, büyük bir tehlike ile karşı karşıya kalınca harekete geçmek zorunda kalır. Ancak bu tehlike ile tek başına baş etmesi zordur. Bu yüzden Wade en az kendisi kadar isteksiz olan Wolverine'i yardım etmesi için ikna etmeye çalışır.",
        "poster_path": "/fVr2X3jnoeLuZ2v0L1O8MOdOiSz.jpg",
        "media_type": "movie",
        "adult": false,
        "original_language": "en",
        "genre_ids": [
          28,
          35,
          878
        ],
        "popularity": 267.281,
        "release_date": "2024-07-24",
        "video": false,
        "vote_average": 7.617,
        "vote_count": 6834
      },
      {
        "backdrop_path": "/iJaSpQNZ8GsqVDWfbCXmyZQXZ5l.jpg",
        "id": 945961,
        "title": "Alien: Romulus",
        "original_title": "Alien: Romulus",
        "overview": "Uzay sömürgecileri Rain, Andy, Tyler, Kay, Bjorn ve Navarro, görünüşte tamamen terk edilmiş gibi gözüken bir uzay istasyonunda bir şeyler bulma umuduyla arama yapar. Ancak onların gerçekte neler olup bittiğine dair hiçbir fikri yoktur. Çok geçmeden grup, dünyanın en korkutucu yaşam formu ile karşılaşacaktır.",
        "poster_path": "/b33nnKl1GSFbao4l3fZDDqsMx0F.jpg",
        "media_type": "movie",
        "adult": false,
        "original_language": "en",
        "genre_ids": [
          27,
          878
        ],
        "popularity": 167.908,
        "release_date": "2024-08-13",
        "video": false,
        "vote_average": 7.2,
        "vote_count": 3407
      },
      {
        "backdrop_path": "/wSZbtiFIK1fkKZdSRtn2kz2Ttfd.jpg",
        "id": 1139817,
        "title": "Siyah Kuşaklı Memur",
        "original_title": "무도실무관",
        "overview": "Zor durumdaki kişileri görmezden gelemeyen hünerli bir dövüş sanatçısı, dövüş sanatları memuru olarak suçla savaşmak ve suçu önlemek için bir şartlı tahliye memuruyla el ele verir.",
        "poster_path": "/wwLALiEazvl29I0HSwinVX6CCVe.jpg",
        "media_type": "movie",
        "adult": false,
        "original_language": "ko",
        "genre_ids": [
          28,
          35,
          80
        ],
        "popularity": 31.756,
        "release_date": "2024-09-12",
        "video": false,
        "vote_average": 7.7,
        "vote_count": 269
      },
      {
        "backdrop_path": "/co7oxvpWxgd6FZU24DnljDDHYQA.jpg",
        "id": 1064028,
        "title": "İtaat",
        "original_title": "Subservience",
        "overview": "Gelişmiş bir yapay zeka sistemi tarafından yönetilen bir toplumu konu alıyor. Bu toplumda insanlar, yapay zekanın belirlediği kurallara uymak zorundadır ve bu durum, insanların yaşamlarını büyük ölçüde kontrol altına alır. Baş karakter olan genç bir kadının, yapay zekanın kendisine ve çevresindekilere uyguladığı baskıya karşı çıkma mücadelesini anlatıyor. Ana karakter, başlangıçta sistemin bir parçası olarak yaşarken zamanla yapay zekanın kararlarının ve etkisinin ne kadar tehlikeli olabileceğini fark eder. Kendisi ve sevdikleri için daha iyi bir gelecek arayışına girer ve bu süreçte, diğer insanları da harekete geçirmeye çalışır.",
        "poster_path": "/gBenxR01Uy0Ev9RTIw6dVBPoyQU.jpg",
        "media_type": "movie",
        "adult": false,
        "original_language": "en",
        "genre_ids": [
          878,
          53
        ],
        "popularity": 91.586,
        "release_date": "2024-08-15",
        "video": false,
        "vote_average": 6.682,
        "vote_count": 634
      },
      {
        "backdrop_path": "/zo8CIjJ2nfNOevqNajwMRO6Hwka.jpg",
        "id": 1241982,
        "title": "Moana 2",
        "original_title": "Moana 2",
        "overview": "Moana ve Maui'yi üç yıl sonra alışılmadık denizcilerden oluşan bir ekiple birlikte geniş kapsamlı yeni bir yolculuk için yeniden bir araya getiriyor. Yol gösterici atalarından beklenmedik bir çağrı alan Moana, daha önce karşılaşmadığı bir macera için Okyanusya'nın uzak denizlerine, tehlikeli ve uzun süredir bilinmeyen sularına yolculuk etmek zorunda.",
        "poster_path": "/3C9jcjZSwRVDk83VgBK7WU5qVQ8.jpg",
        "media_type": "movie",
        "adult": false,
        "original_language": "en",
        "genre_ids": [
          16,
          12,
          10751,
          35
        ],
        "popularity": 1059.555,
        "release_date": "2024-11-21",
        "video": false,
        "vote_average": 7.2,
        "vote_count": 1776
      },
      {
        "backdrop_path": "/pFLs2qFhfp7k2zgT69fTkcl0uHF.jpg",
        "id": 1091181,
        "title": "Kurt Adamlar",
        "original_title": "Loups-Garous",
        "overview": "Eski bir kart oyunu canlanınca bir aile, zamanda geriye giderek kendilerini eve dönebilmek için kurt adamların maskelerini düşürmek zorunda oldukları bir Orta Çağ köyünde bulur.",
        "poster_path": "/ahzWHYdRFqnlpsM5l5qHU4Fj3az.jpg",
        "media_type": "movie",
        "adult": false,
        "original_language": "fr",
        "genre_ids": [
          12,
          35,
          14,
          28
        ],
        "popularity": 20.88,
        "release_date": "2024-10-22",
        "video": false,
        "vote_average": 5.6,
        "vote_count": 405
      },
      {
        "backdrop_path": "/1aOPPkXASkd2By3EKIw66Ilx5qF.jpg",
        "id": 1094974,
        "title": "Take Cover",
        "original_title": "Take Cover",
        "overview": "Tükenmiş profesyonel bir keskin nişancı, ölümcül bir rakip tarafından camdan bir çatı katında sıkışıp kalır ve katille arasında çok az siper varken hayatta kalmanın ve kaçmanın bir yolunu bulmalıdır.",
        "poster_path": "/xNLiMNyFzKTL9PVIEulG55Hei8j.jpg",
        "media_type": "movie",
        "adult": false,
        "original_language": "en",
        "genre_ids": [
          28,
          53
        ],
        "popularity": 49.001,
        "release_date": "2024-10-04",
        "video": false,
        "vote_average": 6.6,
        "vote_count": 107
      }
    ],
    "total_pages": 2,
    "total_results": 40
  }
}